{
  "frameId": "f-sr11-invoice-001",
  "frameType": "result",
  "widgets": [
    {
      "widgetType": "UW-014",
      "data": {
        "summary": "Pulled overdue invoice INV-3382 for Magnolia Home & Garden. Cross-referenced AR aging and reminder history.",
        "steps": [
          { "step": 1, "action": "fetch_overdue_invoices", "result": "1 invoice: INV-3382", "ms": 165 },
          { "step": 2, "action": "fetch_ar_aging", "result": "27 days overdue, 31% of customer AR", "ms": 140 },
          { "step": 3, "action": "fetch_reminder_history", "result": "2 prior reminders sent", "ms": 95 }
        ],
        "mcpsAccessed": ["AR", "CRM"],
        "totalMs": 400
      },
      "config": { "collapsed": true }
    },
    {
      "widgetType": "UW-003",
      "data": {
        "entityType": "invoice",
        "title": "Invoice INV-3382 — Magnolia Home & Garden",
        "fields": [
          { "label": "Customer", "value": "Magnolia Home & Garden (C-8001)", "entityId": "C-8001" },
          { "label": "Amount Due", "value": "$18,200.00" },
          { "label": "Issued", "value": "March 28, 2026" },
          { "label": "Due Date", "value": "April 11, 2026" },
          { "label": "Status", "value": "Overdue (27 days)" },
          { "label": "Original Order", "value": "ORD-90412" }
        ]
      }
    },
    {
      "widgetType": "UW-002",
      "data": {
        "cards": [
          { "label": "Days Overdue", "value": "27", "format": "count" },
          { "label": "Amount", "value": "$18,200", "format": "currency" },
          { "label": "% of Customer AR", "value": "31%", "format": "percent" },
          { "label": "Reminders Sent", "value": "2", "format": "count" }
        ]
      }
    },
    {
      "widgetType": "UW-011",
      "data": {
        "title": "Reminder History",
        "items": [
          { "id": "RM-1", "title": "Auto-reminder #1 sent", "dueDate": "Apr 14", "priority": "Info", "assignedTo": "System", "status": "Sent" },
          { "id": "RM-2", "title": "Auto-reminder #2 sent", "dueDate": "Apr 25", "priority": "Info", "assignedTo": "System", "status": "Sent" },
          { "id": "RM-3", "title": "Manual call by Heman — left voicemail", "dueDate": "May 02", "priority": "Info", "assignedTo": "Heman", "status": "Logged" }
        ]
      }
    },
    {
      "widgetType": "AW-001",
      "data": { "label": "Open Invoice in AR", "url": "/invoices/INV-3382", "style": "secondary" }
    }
  ],
  "closingText": {
    "type": "insight",
    "text": "INV-3382 is 27 days overdue and represents 31% of Magnolia's outstanding AR. Two automated reminders went out and Heman called May 2 with no response. Recommend a personalized email or a follow-up task before escalating to credit hold."
  }
}
