{
    "frameId": "f-uc2-magnolia-001",
    "frameType": "action_staged",
    "widgets": [
        {
            "widgetType": "UW-014",
            "data": {
                "summary": "Intent: Task Creation. Resolved 'Magnolia Home & Garden' -> Customer C-8001. Resolved 'Heman Bhullar' -> User U-0042. Task staged for review.",
                "steps": [
                    { "step": 1, "action": "search_customers", "result": "1 match: C-8001 (Magnolia Home & Garden)", "ms": 145 },
                    { "step": 2, "action": "fetch_customer_360", "result": "Profile loaded — VIP, West Coast, Heman owns", "ms": 180 },
                    { "step": 3, "action": "resolve_user", "result": "U-0042 (Heman Bhullar)", "ms": 120 },
                    { "step": 4, "action": "validate_org_config", "result": "Task types valid, priority valid", "ms": 14 }
                ],
                "mcpsAccessed": ["CRM", "Users"],
                "totalMs": 459
            },
            "config": { "collapsed": true }
        },
        {
            "widgetType": "UW-003",
            "data": {
                "entityType": "task",
                "title": "Follow up with Magnolia Home & Garden",
                "fields": [
                    { "label": "Customer", "value": "Magnolia Home & Garden (Customer)", "entityId": "C-8001" },
                    { "label": "Type", "value": "Follow Up" },
                    { "label": "Priority", "value": "High" },
                    { "label": "Status", "value": "Open" },
                    { "label": "Assigned To", "value": "Heman Bhullar" },
                    { "label": "Due Date", "value": "May 15, 2026" }
                ]
            }
        },
        {
            "widgetType": "AW-004",
            "data": {
                "formId": "task-creation-form",
                "steps": [
                    {
                        "stepTitle": "Task Details",
                        "fields": [
                            { "fieldId": "customer", "type": "entity_search", "label": "Customer", "value": "Magnolia Home & Garden", "resolvedId": "C-8001", "required": true },
                            { "fieldId": "type", "type": "select", "label": "Type", "value": "Follow Up", "options": ["Schedule Call", "Email", "Follow Up", "Site Visit", "Other"], "required": true },
                            { "fieldId": "title", "type": "text", "label": "Title", "value": "Follow up with Magnolia Home & Garden", "required": true },
                            { "fieldId": "assignee", "type": "user_search", "label": "Assigned To", "value": "Heman Bhullar", "resolvedId": "U-0042", "required": true },
                            { "fieldId": "dueDate", "type": "date", "label": "Due Date", "value": "2026-05-15", "required": true },
                            { "fieldId": "priority", "type": "select", "label": "Priority", "value": "High", "options": ["High", "Medium", "Low"], "required": true },
                            { "fieldId": "status", "type": "select", "label": "Status", "value": "Open", "options": ["Open", "In Progress", "Completed", "Hold"], "required": true }
                        ]
                    }
                ]
            },
            "config": { "mode": "review", "editable": false }
        },
        {
            "widgetType": "AW-012",
            "data": {
                "message": "Kai has staged this follow-up task for Magnolia Home & Garden. Confirm to create it.",
                "tier": "draft",
                "actions": ["Confirm & Create", "Edit", "Cancel"]
            }
        }
    ],
    "closingText": {
        "type": "description",
        "text": "I've staged a follow-up task for Magnolia Home & Garden, assigned to Heman with a due date of May 15. Magnolia's last order was 45 days ago — slightly above their VIP cadence — so a follow-up makes sense. Review the details and confirm when ready."
    },
    "actions": {
        "onConfirm": {
            "mcp": "CRM",
            "method": "createTask",
            "payload": {
                "customerId": "C-8001",
                "title": "Follow up with Magnolia Home & Garden",
                "priority": "High",
                "type": "Follow Up",
                "status": "Open",
                "assignedTo": "U-0042",
                "dueDate": "2026-05-15"
            }
        },
        "onCancel": { "action": "discard" },
        "onModify": { "action": "unlock_form" }
    }
}
